auto_feature_prod/.DS_Store
auto_feature_prod/Dockerfile
auto_feature_prod/__init__.py
auto_feature_prod/cli.py
auto_feature_prod/dbhelper.py
auto_feature_prod/docker-compose.yml
auto_feature_prod/ftools.py
auto_feature_prod/get_ft_features.py
auto_feature_prod/helper.py
auto_feature_prod/path.json
auto_feature_prod/requirements.txt
auto_feature_prod/run.py
auto_feature_prod/run_docker.sh
auto_feature_prod/views.py
auto_feature_prod/__pycache__/dbhelper.cpython-38.pyc
auto_feature_prod/__pycache__/ftools.cpython-38.pyc
auto_feature_prod/__pycache__/get_ft_features.cpython-38.pyc
auto_feature_prod/__pycache__/helper.cpython-38.pyc
auto_feature_prod/static/.DS_Store
auto_feature_prod/static/css/Search-icon.png
auto_feature_prod/static/css/bootstrap.min.css
auto_feature_prod/static/css/chosen.css
auto_feature_prod/static/css/chosen.min.css
auto_feature_prod/static/css/favicon.png
auto_feature_prod/static/css/ie10-viewport-bug-workaround.css
auto_feature_prod/static/css/searchicon.png
auto_feature_prod/static/css/selection.css
auto_feature_prod/static/css/sticky-footer-navbar.css
auto_feature_prod/static/css/style.css
auto_feature_prod/static/display/.DS_Store
auto_feature_prod/static/js/.DS_Store
auto_feature_prod/static/js/BsMultiSelect.js
auto_feature_prod/static/js/bootstrap.min.js
auto_feature_prod/static/js/chosen.jquery.js
auto_feature_prod/static/js/chosen.jquery.min.js
auto_feature_prod/static/js/ie-emulation-modes-warning.js
auto_feature_prod/static/js/ie10-viewport-bug-workaround.js
auto_feature_prod/static/js/jquery.dataTables.min.js
auto_feature_prod/static/js/jquery.min.js
auto_feature_prod/static/js/jquery.table2excel.js
auto_feature_prod/static/js/sorttable.js
auto_feature_prod/templates/.DS_Store
auto_feature_prod/templates/data_selection.html
auto_feature_prod/templates/directory.html
auto_feature_prod/templates/favicon.ico
auto_feature_prod/templates/home.html
auto_feature_prod/templates/layout.html
auto_feature_prod/templates/re_directory.html
auto_feature_prod-0.0.1.dist-info/METADATA
auto_feature_prod-0.0.1.dist-info/WHEEL
auto_feature_prod-0.0.1.dist-info/entry_points.txt
auto_feature_prod-0.0.1.dist-info/top_level.txt
auto_feature_prod-0.0.1.dist-info/RECORD
